{
  "abstract": "",
  "accredited": true,
  "authors": [
    "Jean-Baptiste Alayrac",
    "Jeff Donahue",
    "Pauline Luc",
    "Antoine Miech",
    "Iain Barr",
    "Yana Hasson",
    "Karel Lenc",
    "Arthur Mensch",
    "Katherine Millican",
    "Malcolm Reynolds",
    "Roman Ring",
    "Eliza Rutherford",
    "Serkan Cabi",
    "Tengda Han",
    "Zhitao Gong",
    "Sina Samangooei",
    "Marianne Monteiro",
    "Jacob L Menick",
    "Sebastian Borgeaud",
    "Andy Brock",
    "Aida Nematzadeh",
    "Sahand Sharifzadeh",
    "Mikolaj Binkowski",
    "Ricardo Barreira",
    "Oriol Vinyals",
    "Andrew Zisserman",
    "Karén Simonyan"
  ],
  "registrar": "crossref",
  "retrieval": {
    "canon_id": "flamingo-2022",
    "fetched_at": "2026-07-06T07:39:40.716796+00:00",
    "method": "crossref-title"
  },
  "source_type": "proceedings-article",
  "text_sha256": "764ef67912eba019267f4ffe6234d555874f79e100b7841f5e687ceea902dbea",
  "title": "Flamingo: A Visual Language Model for Few-Shot Learning",
  "url": "https://doi.org/10.52202/068431-1723",
  "venue": "Advances in Neural Information Processing Systems 35",
  "work_id": "doi:10.52202/068431-1723",
  "year": 2022
}
