{"artifact":["artifacts/oee.json"],"caveat":"OEE is pure ratio arithmetic (Availability x Performance x Quality); the module fails closed on non-positive denominators and on factors above 1 (run > planned, good > total, ideal cycle too large), but it does not model the six big losses, planned vs unplanned stop classification, or multi-shift roll-ups. Values are compared to 4 decimal places; correctness is demonstrated over a fixed reference table, not proven for every input.","evidence_level":"measured","id":"CLAIM-LIB-OEE-001","metrics":{"correct":3,"errors":0,"n_cases":3},"statement":"The vendored OEE calculator reproduces the canonical published worked example (Vorne / oee.com) exactly to 4 dp -- Availability 0.8881, Performance 0.8611, Quality 0.9780, OEE 0.7479 from Planned 420 min, Run 373 min, Ideal Cycle 1.0 s, Total 19271, Good 18848 -- and matches all 3 hand-computed reference cases (correct = 3, errors = 0), including the perfect-line boundary (all factors 1.0) and the each-factor-one-half case (OEE 0.125)."}